Workbook

Sheet Expense
A1: Date | B1: Items | C1: Expenses | D1: Category | E1: Cost Type
A2: 44470 | B2: Medicine | C2: 2300 | D2: Essential | E2: =IF(C2>2000,"Over Budget", "Within Budget") -> Over Budget
A3: 44470 | B3: Online shopping | C3: 767 | D3: Non-Essential | E3: =IF(C3>2000,"Over Budget", "Within Budget") -> Within Budget
A4: 44470 | B4: Other essential items | C4: 2500 | D4: Essential | E4: =IF(C4>2000,"Over Budget", "Within Budget") -> Over Budget
A5: 44473 | B5: Vegetables & Fruit | C5: 710 | D5: Essential | E5: =IF(C5>2000,"Over Budget", "Within Budget") -> Within Budget
A6: 44473 | B6: Fish & Chicken | C6: 760 | D6: Non-Essential | E6: =IF(C6>2000,"Over Budget", "Within Budget") -> Within Budget
A7: 44476 | B7: Gifts | C7: 1900 | D7: Non-Essential | E7: =IF(C7>2000,"Over Budget", "Within Budget") -> Within Budget
A8: 44477 | B8: Ordering food | C8: 450 | D8: Non-Essential | E8: =IF(C8>2000,"Over Budget", "Within Budget") -> Within Budget
A9: 44484 | B9: Movie with friends | C9: 620 | D9: Non-Essential | E9: =IF(C9>2000,"Over Budget", "Within Budget") -> Within Budget
A10: 44485 | B10: Mobile Bill Payment | C10: 470 | D10: Non-Essential | E10: =IF(C10>2000,"Over Budget", "Within Budget") -> Within Budget
A11: 44487 | B11: Online shopping | C11: 970 | D11: Non-Essential | E11: =IF(C11>2000,"Over Budget", "Within Budget") -> Within Budget
A12: 44487 | B12: Medicine | C12: 1075 | D12: Essential | E12: =IF(C12>2000,"Over Budget", "Within Budget") -> Within Budget
A13: 44488 | B13: Ordering food | C13: 489 | D13: Non-Essential | E13: =IF(C13>2000,"Over Budget", "Within Budget") -> Within Budget
... A51: 44553 | B51: Vegetables & Fruit | C51: 450 | D51: Essential | E51: =IF(C51>2000,"Over Budget", "Within Budget") -> Within Budget
C52: =SUM(C2:C51) -> 57045.27
I53: Items | J53: Expense
I54: Medicine | J54: 2300
I55: Online shopping | J55: 767
I56: Other essential items | J56: 2500
I57: Vegetables & Fruit | J57: 710
I58: Fish & Chicken | J58: 760
I59: Gifts | J59: 1900
I60: Ordering food | J60: 450
I61: Movie with friends | J61: 620
I62: Mobile Bill Payment | J62: 470
I63: Online shopping | J63: 970
I64: Medicine | J64: 1075
I65: Ordering food | J65: 489
... I103: Vegetables & Fruit | J103: 450

Sheet Tasks
B1: Task to Perform
B2: How many times has Priya done transactions on online shopping, ordering food and gifts?
B3: Calculate the total expenses against each distinct item.
B4: Arrange the item-wise total expense in descending order.
B5: Present the item-wise total expense through a chart that shows the expense of each item as a percentage of the total expense. Don’t take trip expenses into consideration.
B6: Present the expense pattern visually over 3 months.
B7: Add a new column to the data table, name it as “Category” and apply data validation with drop-down fields as “Essentials” and “Non-essentials”. Fill in the column.
B8: Add another new column and name it as “Cost Type”. For each item, if the expense is more than 2000, tag it as “Over budget”, else, tag it as “Within budget”.
B9: Mention the ways how Priya can reduce her expenses. Justify each point.

Sheet Sheet1
A1: Q1: | B1: How many times has Priya done transactions on online shopping, ordering food and gifts?
C3: Online shopping: | D3: =COUNTIF(Expense!B:B,Expense!I55) -> 6
C4: Ordering food: | D4: =COUNTIF(Expense!B:B,Expense!I60) -> 5
C5: Gifts: | D5: =COUNTIF(Expense!B:B,Expense!I59) -> 4
A9: Q2: | B9: Calculate the total expenses against each distinct item.
C10: Items | D10: Expenses
C11: Medicine: | D11: =SUMIF(Expense!B:B,Expense!I54,Expense!J53) -> 7775
C12: Online shopping: | D12: =SUMIF(Expense!B:B,Expense!I55,Expense!J53) -> 7464
C13: Other essential items: | D13: =SUMIF(Expense!B:B,Expense!I66,Expense!J53) -> 10194.1
C14: Vegetables & Fruit: | D14: =SUMIF(Expense!B:B,Expense!I57,Expense!J53) -> 3217
C15: Fish & Chicken: | D15: =SUMIF(Expense!B:B,Expense!I58,Expense!J53) -> 3342
C16: Gifts: | D16: =SUMIF(Expense!B:B,Expense!I59,Expense!J53) -> 5688
C17: Ordering food: | D17: =SUMIF(Expense!B:B,Expense!I60,Expense!J53) -> 1857
C18: Movie with friends: | D18: =SUMIF(Expense!B:B,Expense!I61,Expense!J53) -> 2586
C19: Mobile Bill Payment: | D19: =SUMIF(Expense!B:B,Expense!I62,Expense!J53) -> 1411.26
C20: Cab to office: | D20: =SUMIF(Expense!B:B,Expense!I68,Expense!J53) -> 1510.91
C21: Trip: | D21: =SUMIF(Expense!B:B,Expense!I98,Expense!J53) -> 12000
A24: Q3: | B24: Arrange the item-wise total expense in descending order.
C26: Items | D26: Expenses
C27: Trip: | D27: 12000
C28: Other essential items: | D28: 10194.1
C29: Medicine: | D29: 7775
C30: Online shopping: | D30: 7464
C31: Gifts: | D31: 5688
C32: Fish & Chicken: | D32: 3342
C33: Vegetables & Fruit: | D33: 3217
C34: Movie with friends: | D34: 2586
C35: Ordering food: | D35: 1857
C36: Cab to office: | D36: 1510.91
C37: Mobile Bill Payment: | D37: 1411.26
F67: Medicine | G67: 2300
G87: Trip | H87: 12000
G88: Gifts | H88: 1500
G89: Mobile Bill Payment | H89: 470.63
G90: Ordering food | H90: 267
G91: Fish & Chicken | H91: 640
G92: Vegetables & Fruit | H92: 450
